modlyn/__init__.py
modlyn/eval/__init__.py
modlyn/eval/_jaccard.py
modlyn/models/__init__.py
modlyn/models/_simple_logreg_datamodule.py
modlyn/models/_simple_logreg_model.py
modlyn-0.0.7.dist-info/LICENSE
modlyn-0.0.7.dist-info/WHEEL
modlyn-0.0.7.dist-info/METADATA
modlyn-0.0.7.dist-info/RECORD
