Metadata-Version: 2.3
Name: modlyn
Version: 0.0.7
Summary: Modlyn.
Author-email: Lamin Labs <open-source@lamin.ai>
Requires-Python: >=3.9,<3.13
Requires-Dist: anndata>=0.12.0rc1
Requires-Dist: scikit-learn
Requires-Dist: matplotlib
Requires-Dist: lightning
Requires-Dist: lamindb[jupyter] ; extra == "dev"
Requires-Dist: seaborn ; extra == "dev"
Requires-Dist: pre-commit ; extra == "dev"
Requires-Dist: nox ; extra == "dev"
Requires-Dist: pytest>=6.0 ; extra == "dev"
Requires-Dist: pytest-cov ; extra == "dev"
Requires-Dist: nbproject_test ; extra == "dev"
Project-URL: Home, https://github.com/laminlabs/modlyn
Provides-Extra: dev
